odoo10_addon_purchase_request_to_rfq_order_approved-10.0.1.0.0.99.dev2-py2.7-nspkg.pth
odoo/addons/purchase_request_to_rfq_order_approved/README.rst
odoo/addons/purchase_request_to_rfq_order_approved/__init__.py
odoo/addons/purchase_request_to_rfq_order_approved/__manifest__.py
odoo/addons/purchase_request_to_rfq_order_approved/init_hook.py
odoo/addons/purchase_request_to_rfq_order_approved/i18n/es.po
odoo/addons/purchase_request_to_rfq_order_approved/i18n/fr.po
odoo/addons/purchase_request_to_rfq_order_approved/i18n/purchase_request_to_rfq_order_approved.pot
odoo/addons/purchase_request_to_rfq_order_approved/i18n/sl.po
odoo/addons/purchase_request_to_rfq_order_approved/models/__init__.py
odoo/addons/purchase_request_to_rfq_order_approved/models/purchase_request.py
odoo/addons/purchase_request_to_rfq_order_approved/static/description/icon.png
odoo/addons/purchase_request_to_rfq_order_approved/tests/__init__.py
odoo/addons/purchase_request_to_rfq_order_approved/tests/test_purchase_request_to_rfq_order_approved.py
odoo/addons/purchase_request_to_rfq_order_approved/views/purchase_request_view.xml
odoo10_addon_purchase_request_to_rfq_order_approved-10.0.1.0.0.99.dev2.dist-info/METADATA
odoo10_addon_purchase_request_to_rfq_order_approved-10.0.1.0.0.99.dev2.dist-info/RECORD
odoo10_addon_purchase_request_to_rfq_order_approved-10.0.1.0.0.99.dev2.dist-info/WHEEL
odoo10_addon_purchase_request_to_rfq_order_approved-10.0.1.0.0.99.dev2.dist-info/namespace_packages.txt
odoo10_addon_purchase_request_to_rfq_order_approved-10.0.1.0.0.99.dev2.dist-info/top_level.txt
